[
  {
    "id": "proj-coulisseau",
    "title": "Remplacement d’un coulisseau de lève-vitre cassé",
    "thumbnail": "images/projects/leve-vitre-card.jpg",
    "gallery": [
      "images/projects/leve-vitre-1.jpg",
      "images/projects/leve-vitre-2.jpg"
    ],
    "summary": "Recréation sur-mesure d’un coulisseau de fenêtre pour camping-car Ford Challenger avec validation fonctionnelle.",
    "description": "Un propriétaire de camping-car ne trouvait plus la pièce de rechange pour son coulisseau de lève-vitre électrique. Nous avons reconstitué la pièce d’origine à partir de mesures et d’un scan 3D, conçu un modèle optimisé puis produit une version renforcée en impression FDM. Après plusieurs itérations de tests, la pièce a été validée et réinstallée dans le mécanisme d’origine.",
    "highlights": [
      "Prise de cotes et rétro-conception complète",
      "Modélisation CAO paramétrique pour itérations rapides",
      "Impression 3D FDM PLA+ renforcé et contrôle qualité"
    ],
    "services": [
      "Modélisation CAO",
      "Impression 3D"
    ],
    "cta": "Commander une pièce similaire",
    "ctaLink": "commandes.html?type=remplacement"
  },
  {
    "id": "proj-multimaterial",
    "title": "Impression 3D multi-matériaux pour pièces fonctionnelles",
    "thumbnail": "images/projects/multi-materiaux-card.jpg",
    "gallery": [
      "images/projects/multi-materiaux-1.jpg",
      "images/projects/multi-materiaux-2.jpg"
    ],
    "summary": "Production de pièces mixtes PLA/TPU assemblées et testées mécaniquement pour un prototype industriel.",
    "description": "Nous avons accompagné un bureau d’études sur un prototype mêlant pièces rigides et flexibles. Les géométries ont été optimisées pour l’assemblage, l’étanchéité et la maintenance. Les séries ont été produites puis testées mécaniquement pour valider la tenue à l’effort et aux environnements contraints.",
    "highlights": [
      "Optimisation topologique et tolérances d’assemblage",
      "Paramétrage avancé multi-matériaux",
      "Tests mécaniques et rapport de validation"
    ],
    "services": [
      "Modélisation CAO",
      "Impression 3D"
    ],
    "cta": "Lancer un prototype",
    "ctaLink": "commandes.html?type=prototype"
  }
]